abdulkerim/__init__.py
abdulkerim/main.py
abdulkerim-0.3.dist-info/METADATA
abdulkerim-0.3.dist-info/WHEEL
abdulkerim-0.3.dist-info/entry_points.txt
abdulkerim-0.3.dist-info/top_level.txt
abdulkerim-0.3.dist-info/RECORD
