Metadata-Version: 2.1
Name: abdulkerim
Version: 0.3
Summary: Fun
Author: Ali Cenk Baytop
Author-email: baytop.alicenk@gmail.com
